{
  "name": "Bazel Development Environment",
  "image": "mcr.microsoft.com/devcontainers/base:ubuntu-24.04",
  "mounts": [
    "source=bazel-cache,target=/home/vscode/.cache/bazel,type=volume",
    "source=bazelisk-cache,target=/home/vscode/.cache/bazelisk,type=volume",
  ],
  "onCreateCommand": "./.devcontainer/on_create.sh",
  "postCreateCommand": "./.devcontainer/post_create.sh",
  "features": {
    "ghcr.io/devcontainers/features/common-utils:2": {
      "installZsh": true,
      "configureZshAsDefaultShell": true,
      "installOhMyZsh": false,
      "installOhMyZshConfig": false
      // Get your own dotfiles configured with
      // https://code.visualstudio.com/docs/devcontainers/containers#_personalizing-with-dotfile-repositories
    },
    "ghcr.io/devcontainers/features/git:1": {},
    "ghcr.io/rocker-org/devcontainer-features/apt-packages:1": {
      "upgradePackages": true,
      "packages": [
        "direnv",
        "musl-tools"
      ]
    }
  },
  "customizations": {
    "vscode": {
      "extensions": [
        "BazelBuild.vscode-bazel",
        "eamodio.gitlens",
        "yzhang.markdown-all-in-one"
      ],
    }
  },
}
